infi.exceptools-0.2.15-py2.7-nspkg.pth
infi/exceptools/__init__.py
infi/exceptools/__version__.py
infi/exceptools/noseplugin.py
infi/exceptools/py2.py
infi/exceptools/py3.py
infi.exceptools-0.2.15.dist-info/LICENSE
infi.exceptools-0.2.15.dist-info/METADATA
infi.exceptools-0.2.15.dist-info/WHEEL
infi.exceptools-0.2.15.dist-info/entry_points.txt
infi.exceptools-0.2.15.dist-info/namespace_packages.txt
infi.exceptools-0.2.15.dist-info/top_level.txt
infi.exceptools-0.2.15.dist-info/RECORD
